quasi_poisson/__init__.py
quasi_poisson/quasi_poisson.py
quasi_poisson-0.1.0.dist-info/LICENSE.txt
quasi_poisson-0.1.0.dist-info/METADATA
quasi_poisson-0.1.0.dist-info/WHEEL
quasi_poisson-0.1.0.dist-info/top_level.txt
quasi_poisson-0.1.0.dist-info/RECORD
