Metadata-Version: 2.1
Name: quasi_poisson
Version: 0.1.0
Summary: Estimate Quasi-Poisson Regression Model
Home-page: https://github.com/statcompute/quasi_poisson
Author: WenSui Liu
Author-email: liuwensui@gmail.com
Classifier: Programming Language :: Python :: 3
Classifier: License :: OSI Approved :: MIT License
Classifier: Operating System :: OS Independent
License-File: LICENSE.txt
Requires-Dist: statsmodels
Requires-Dist: numpy
Requires-Dist: scipy
Requires-Dist: pandas
